{
  "display": {
    "icon": {
      "item": "better_tools:netherite_energy_vial"
    },
    "title": {
      "translate": "advancements.all_diamond_effect_armor_adv.title"
    },
    "description": {
      "translate": "advancements.all_diamond_effect_armor_adv.descr"
    },
    "frame": "challenge",
    "show_toast": true,
    "announce_to_chat": true,
    "hidden": false
  },
  "criteria": {
    "all_diamond_effect_armor_adv_0": {
      "trigger": "minecraft:impossible"
    }
  },
  "rewards": {
    "experience": 100
  },
  "parent": "better_tools:emerald_energy_vial_adv"
}